README.rst
setup.py
bin/nopaths
nopaths/__init__.py
nopaths/__main__.py
nopaths/clients.py
nopaths/clocked.py
nopaths/command.py
nopaths/configs.py
nopaths/decoder.py
nopaths/default.py
nopaths/defines.py
nopaths/encoder.py
nopaths/errored.py
nopaths/handler.py
nopaths/listens.py
nopaths/logging.py
nopaths/message.py
nopaths/objects.py
nopaths/objfunc.py
nopaths/parsers.py
nopaths/persist.py
nopaths/repeats.py
nopaths/runtime.py
nopaths/threads.py
nopaths/utility.py
nopaths.egg-info/PKG-INFO
nopaths.egg-info/SOURCES.txt
nopaths.egg-info/dependency_links.txt
nopaths.egg-info/top_level.txt
nopaths.egg-info/zip-safe
nopaths/modules/__init__.py
nopaths/modules/cfg.py
nopaths/modules/cmd.py
nopaths/modules/err.py
nopaths/modules/flt.py
nopaths/modules/fnd.py
nopaths/modules/irc.py
nopaths/modules/log.py
nopaths/modules/mod.py
nopaths/modules/rss.py
nopaths/modules/sts.py
nopaths/modules/tdo.py
nopaths/modules/thr.py
nopaths/modules/upt.py
nopaths/modules/ver.py
test/test_composite.py
test/test_decoder.py
test/test_encoder.py
test/test_inherit.py
test/test_objects.py
test/test_recursive.py
test/test_storage.py